README.md
setup.cfg
setup.py
wwpdb/__init__.py
wwpdb.apps.chem_ref_data.egg-info/PKG-INFO
wwpdb.apps.chem_ref_data.egg-info/SOURCES.txt
wwpdb.apps.chem_ref_data.egg-info/dependency_links.txt
wwpdb.apps.chem_ref_data.egg-info/not-zip-safe
wwpdb.apps.chem_ref_data.egg-info/requires.txt
wwpdb.apps.chem_ref_data.egg-info/top_level.txt
wwpdb/apps/__init__.py
wwpdb/apps/chem_ref_data/README.md
wwpdb/apps/chem_ref_data/__init__.py
wwpdb/apps/chem_ref_data/depict/ChemRefDataDepict.py
wwpdb/apps/chem_ref_data/depict/ChemRefDataDepictBootstrap.py
wwpdb/apps/chem_ref_data/depict/__init__.py
wwpdb/apps/chem_ref_data/io/__init__.py
wwpdb/apps/chem_ref_data/report/BirdReport.py
wwpdb/apps/chem_ref_data/report/ChemCompReport.py
wwpdb/apps/chem_ref_data/report/ChemRefReportDepictBootstrap.py
wwpdb/apps/chem_ref_data/report/ReportUtils.py
wwpdb/apps/chem_ref_data/report/__init__.py
wwpdb/apps/chem_ref_data/search/ChemCompSearchIndexUtils.py
wwpdb/apps/chem_ref_data/search/ChemRefSearch.py
wwpdb/apps/chem_ref_data/search/ChemRefSearchBase.py
wwpdb/apps/chem_ref_data/search/ChemRefSearchDef.py
wwpdb/apps/chem_ref_data/search/ChemRefSearchDepictBootstrap.py
wwpdb/apps/chem_ref_data/search/ChemRefSearchDuplicates.py
wwpdb/apps/chem_ref_data/search/MiscUtils.py
wwpdb/apps/chem_ref_data/search/__init__.py
wwpdb/apps/chem_ref_data/utils/ChemRefDataCvsUtils.py
wwpdb/apps/chem_ref_data/utils/ChemRefDataDbExec.py
wwpdb/apps/chem_ref_data/utils/ChemRefDataDbUtils.py
wwpdb/apps/chem_ref_data/utils/ChemRefDataMiscUtils.py
wwpdb/apps/chem_ref_data/utils/DownloadUtils.py
wwpdb/apps/chem_ref_data/utils/OSVersion.py
wwpdb/apps/chem_ref_data/utils/__init__.py
wwpdb/apps/chem_ref_data/webapp/ChemRefDataWebApp.py
wwpdb/apps/chem_ref_data/webapp/__init__.py