Metadata-Version: 2.4
Name: wwpdb.apps.chem_ref_data
Version: 0.23.1
Summary: wwPDB chemical reference admin application
Home-page: https://github.com/rcsb/py-wwpdb_apps_chem_ref_data
Author: Ezra Peisach
Author-email: ezra.peisach@rcsb.org
License: Apache 2.0
Classifier: Development Status :: 3 - Alpha
Classifier: Intended Audience :: Developers
Classifier: Natural Language :: English
Classifier: License :: OSI Approved :: Apache Software License
Classifier: Programming Language :: Python
Classifier: Programming Language :: Python :: 2.7
Classifier: Programming Language :: Python :: 3
Classifier: Programming Language :: Python :: 3.6
Classifier: Programming Language :: Python :: 3.7
Requires-Dist: wwpdb.utils.config~=0.34
Requires-Dist: wwpdb.utils.db~=0.26
Requires-Dist: wwpdb.utils.session~=0.4
Requires-Dist: wwpdb.io<2.0,>=0.26
Requires-Dist: mmcif.utils~=0.18
Requires-Dist: wwpdb.utils.oe_util
Requires-Dist: jellyfish~=0.6.1; python_version < "3"
Requires-Dist: jellyfish~=1.0; python_version >= "3"
Requires-Dist: wwpdb.utils.cc_dict_util
Requires-Dist: wwpdb.utils.dp~=0.19
Requires-Dist: rcsb.utils.multiproc
Requires-Dist: wwpdb.utils.ws_utils
Requires-Dist: distro
Provides-Extra: dev
Requires-Dist: check-manifest; extra == "dev"
Provides-Extra: test
Requires-Dist: coverage; extra == "test"
Dynamic: author
Dynamic: author-email
Dynamic: classifier
Dynamic: description
Dynamic: home-page
Dynamic: license
Dynamic: provides-extra
Dynamic: requires-dist
Dynamic: summary
